README.md
setup.cfg
setup.py
economypackage/__init__.py
economypackage/mathseconomy/__init__.py
economypackage/mathseconomy/mathadvancedfuncs.py
economypackage/mathseconomy/mymathsutils.py
victorexample.egg-info/PKG-INFO
victorexample.egg-info/SOURCES.txt
victorexample.egg-info/dependency_links.txt
victorexample.egg-info/requires.txt
victorexample.egg-info/top_level.txt