Metadata-Version: 1.0
Name: victorexample
Version: 0.1
Summary: Paquete que contiene funciones utiles para selección de instancias
Home-page: https://github.com/VicBoxMS/SeleccionDeInstancias
Author: Victor Martinez Santiago @vicbox01
Author-email: UNKNOWN
License: MIT
Platform: UNKNOWN
